cpustresser
stressypy
