Metadata-Version: 1.1
Name: stressypy
Version: 0.0.10
Summary: A simple program for calling stress and/or stress-ng from python
Home-page: https://github.com/salbrandi/stressypy
Author: Salvador Brandi
Author-email: salbrandi@gmail.com
License: UNKNOWN
Download-URL: https://github.com/salbrandi/stressypy/archive/0.1.tar.gz
Keywords: cpu stress cores stress-ng test loads object rq
Platform: UNKNOWN
Classifier: Development Status :: 3 - Alpha
Classifier: Programming Language :: Python :: 3 :: Only
